freezer_tempest_plugin/README.rst
freezer_tempest_plugin/__init__.py
freezer_tempest_plugin/clients.py
freezer_tempest_plugin/common.py
freezer_tempest_plugin/config.py
freezer_tempest_plugin/plugin.py
freezer_tempest_plugin/services/__init__.py
freezer_tempest_plugin/services/freezer_api_client.py
freezer_tempest_plugin/tests/__init__.py
freezer_tempest_plugin/tests/freezer/__init__.py
freezer_tempest_plugin/tests/freezer/agent/__init__.py
freezer_tempest_plugin/tests/freezer/agent/base.py
freezer_tempest_plugin/tests/freezer/agent/test_backup_compress.py
freezer_tempest_plugin/tests/freezer/agent/test_fs_backup.py
freezer_tempest_plugin/tests/freezer/agent/test_metadata_checksum.py
freezer_tempest_plugin/tests/freezer/agent/test_swift_backup.py
freezer_tempest_plugin/tests/freezer/agent/test_tests_running.py
freezer_tempest_plugin/tests/freezer/scenario/__init__.py
freezer_tempest_plugin/tests/freezer/scenario/test_backups.py
freezer_tempest_plugin/tests/freezer_api/__init__.py
freezer_tempest_plugin/tests/freezer_api/api/__init__.py
freezer_tempest_plugin/tests/freezer_api/api/base.py
freezer_tempest_plugin/tests/freezer_api/api/test_api_actions.py
freezer_tempest_plugin/tests/freezer_api/api/test_api_backups.py
freezer_tempest_plugin/tests/freezer_api/api/test_api_clients.py
freezer_tempest_plugin/tests/freezer_api/api/test_api_jobs.py
freezer_tempest_plugin/tests/freezer_api/api/test_api_sessions.py
freezer_tempest_plugin/tests/freezer_api/api/test_api_version.py
freezer_tempest_plugin/tests/freezerclient/__init__.py
freezer_tempest_plugin/tests/freezerclient/base.py
freezer_tempest_plugin/tests/freezerclient/test_freezer_cmd_action.py
freezer_tempest_plugin/tests/freezerclient/test_freezer_cmd_backup.py
freezer_tempest_plugin/tests/freezerclient/test_freezer_cmd_client.py
freezer_tempest_plugin/tests/freezerclient/test_freezer_cmd_job.py
freezer_tempest_plugin/tests/freezerclient/test_freezer_cmd_session.py
freezer_tempest_plugin/tests/scheduler/__init__.py
freezer_tempest_plugin-3.3.0.dist-info/AUTHORS
freezer_tempest_plugin-3.3.0.dist-info/LICENSE
freezer_tempest_plugin-3.3.0.dist-info/METADATA
freezer_tempest_plugin-3.3.0.dist-info/WHEEL
freezer_tempest_plugin-3.3.0.dist-info/entry_points.txt
freezer_tempest_plugin-3.3.0.dist-info/pbr.json
freezer_tempest_plugin-3.3.0.dist-info/top_level.txt
freezer_tempest_plugin-3.3.0.dist-info/RECORD
