Metadata-Version: 2.1
Name: freezer_tempest_plugin
Version: 3.3.0
Summary: Tempest plugin for the freezer project
Home-page: https://docs.openstack.org/tempest/latest/plugin-registry.html
Author: OpenStack
Author-email: openstack-discuss@lists.openstack.org
Classifier: Environment :: OpenStack
Classifier: Intended Audience :: Information Technology
Classifier: Intended Audience :: System Administrators
Classifier: License :: OSI Approved :: Apache Software License
Classifier: Operating System :: POSIX :: Linux
Classifier: Programming Language :: Python
Classifier: Programming Language :: Python :: Implementation :: CPython
Classifier: Programming Language :: Python :: 3 :: Only
Classifier: Programming Language :: Python :: 3
Classifier: Programming Language :: Python :: 3.10
Classifier: Programming Language :: Python :: 3.11
Classifier: Programming Language :: Python :: 3.12
Classifier: Programming Language :: Python :: 3.13
Requires-Python: >=3.10
License-File: LICENSE
License-File: AUTHORS
Requires-Dist: pbr !=2.1.0,>=2.0.0
Requires-Dist: oslo.serialization >=2.25.0
Requires-Dist: oslo.utils >=3.33.0
Requires-Dist: oslo.config >=5.2.0
Requires-Dist: paramiko >=2.0.0
Requires-Dist: tempest >=17.1.0
